README.md
setup.py
selfsne/__init__.py
selfsne/data.py
selfsne/kernels.py
selfsne/likelihood.py
selfsne/losses.py
selfsne/neighbors.py
selfsne/nn.py
selfsne/noise.py
selfsne/prior.py
selfsne/selfsne.py
selfsne/utils.py
selfsne.egg-info/PKG-INFO
selfsne.egg-info/SOURCES.txt
selfsne.egg-info/dependency_links.txt
selfsne.egg-info/not-zip-safe
selfsne.egg-info/requires.txt
selfsne.egg-info/top_level.txt