Metadata-Version: 1.2
Name: selfsne
Version: 0.0.1
Summary: Self-Supervised Noise Embeddings (Self-SNE) for dimensionality reduction and clustering
Home-page: https://github.com/jgraving/selfsne
Author: Jacob Graving <jgraving@gmail.com>
Author-email: jgraving@gmail.com
Maintainer: Jacob Graving <jgraving@gmail.com>
Maintainer-email: jgraving@gmail.com
License: Apache 2.0
Download-URL: https://github.com/jgraving/selfsne.git
Platform: UNKNOWN
Classifier: Intended Audience :: Science/Research
Classifier: Programming Language :: Python :: 3
Classifier: Operating System :: Unix
Classifier: Operating System :: MacOS
